OctoBot_Tulipy-0.4.10.dist-info/AUTHORS
OctoBot_Tulipy-0.4.10.dist-info/RECORD
OctoBot_Tulipy-0.4.10.dist-info/WHEEL
OctoBot_Tulipy-0.4.10.dist-info/top_level.txt
OctoBot_Tulipy-0.4.10.dist-info/LICENSE
OctoBot_Tulipy-0.4.10.dist-info/METADATA
tulipy/lib.cpython-311-x86_64-linux-gnu.so
tulipy/__init__.py
