Metadata-Version: 2.1
Name: OctoBot-Tulipy
Version: 0.4.10
Summary: Financial Technical Analysis Indicator Library. Python bindings for https://github.com/TulipCharts/tulipindicators
Home-page: https://github.com/Drakkar-Software/tulipy
Author: Drakkar-Software
License: LGPL-3.0
Classifier: Development Status :: 4 - Beta
Classifier: Intended Audience :: Developers
Classifier: Intended Audience :: Financial and Insurance Industry
Classifier: License :: OSI Approved :: GNU Lesser General Public License v3 (LGPLv3)
Classifier: Operating System :: OS Independent
Classifier: Programming Language :: Cython
Classifier: Programming Language :: Python :: 3
Classifier: Topic :: Office/Business :: Financial
Classifier: Topic :: Scientific/Engineering :: Information Analysis
License-File: LICENSE
License-File: AUTHORS
